{"moduleName":null,"summaries":[{"symbol":{"__symbol":0,"members":[]},"metadata":{"__symbolic":"class","members":{"elementType":[{"__symbolic":"property","decorators":[{"__symbolic":"call","expression":{"__symbolic":"resolved","symbol":{"__symbol":1,"members":[]},"line":14,"character":3,"fileName":"src/components/qrcode/qrcode.ts"},"arguments":["type"]}]}],"cssClass":[{"__symbolic":"property","decorators":[{"__symbolic":"call","expression":{"__symbolic":"resolved","symbol":{"__symbol":1,"members":[]},"line":15,"character":3,"fileName":"src/components/qrcode/qrcode.ts"},"arguments":["qrc-class"]}]}],"value":[{"__symbolic":"property","decorators":[{"__symbolic":"call","expression":{"__symbolic":"resolved","symbol":{"__symbol":1,"members":[]},"line":16,"character":3,"fileName":"src/components/qrcode/qrcode.ts"},"arguments":["value"]}]}],"version":[{"__symbolic":"property","decorators":[{"__symbolic":"call","expression":{"__symbolic":"resolved","symbol":{"__symbol":1,"members":[]},"line":17,"character":3,"fileName":"src/components/qrcode/qrcode.ts"},"arguments":["version"]}]}],"errorCorrectionLevel":[{"__symbolic":"property","decorators":[{"__symbolic":"call","expression":{"__symbolic":"resolved","symbol":{"__symbol":1,"members":[]},"line":19,"character":3,"fileName":"src/components/qrcode/qrcode.ts"},"arguments":["errorCorrectionLevel"]}]}],"margin":[{"__symbolic":"property","decorators":[{"__symbolic":"call","expression":{"__symbolic":"resolved","symbol":{"__symbol":1,"members":[]},"line":20,"character":3,"fileName":"src/components/qrcode/qrcode.ts"},"arguments":["margin"]}]}],"scale":[{"__symbolic":"property","decorators":[{"__symbolic":"call","expression":{"__symbolic":"resolved","symbol":{"__symbol":1,"members":[]},"line":21,"character":3,"fileName":"src/components/qrcode/qrcode.ts"},"arguments":["scale"]}]}],"width":[{"__symbolic":"property","decorators":[{"__symbolic":"call","expression":{"__symbolic":"resolved","symbol":{"__symbol":1,"members":[]},"line":22,"character":3,"fileName":"src/components/qrcode/qrcode.ts"},"arguments":["width"]}]}],"colorDark":[{"__symbolic":"property","decorators":[{"__symbolic":"call","expression":{"__symbolic":"resolved","symbol":{"__symbol":1,"members":[]},"line":23,"character":3,"fileName":"src/components/qrcode/qrcode.ts"},"arguments":["colorDark"]}]}],"colorLight":[{"__symbolic":"property","decorators":[{"__symbolic":"call","expression":{"__symbolic":"resolved","symbol":{"__symbol":1,"members":[]},"line":24,"character":3,"fileName":"src/components/qrcode/qrcode.ts"},"arguments":["colorLight"]}]}],"qrcElement":[{"__symbolic":"property","decorators":[{"__symbolic":"call","expression":{"__symbolic":"resolved","symbol":{"__symbol":2,"members":[]},"line":26,"character":3,"fileName":"src/components/qrcode/qrcode.ts"},"arguments":["qrcElement"]}]}],"__ctor__":[{"__symbolic":"constructor","parameters":[{"__symbolic":"resolved","symbol":{"__symbol":3,"members":[]},"line":29,"character":32,"fileName":"src/components/qrcode/qrcode.ts"}]}],"ngOnChanges":[{"__symbolic":"method"}],"toDataURL":[{"__symbolic":"method"}],"toCanvas":[{"__symbolic":"method"}],"renderElement":[{"__symbolic":"method"}],"createQRCode":[{"__symbolic":"method"}]}},"type":{"summaryKind":1,"type":{"reference":{"__symbol":0,"members":[]},"diDeps":[{"isAttribute":false,"isHost":false,"isSelf":false,"isSkipSelf":false,"isOptional":false,"token":{"identifier":{"reference":{"__symbol":3,"members":[]}}}}],"lifecycleHooks":[3]},"isComponent":true,"selector":"qrcode","exportAs":null,"inputs":{"elementType":"type","cssClass":"qrc-class","value":"value","version":"version","errorCorrectionLevel":"errorCorrectionLevel","margin":"margin","scale":"scale","width":"width","colorDark":"colorDark","colorLight":"colorLight"},"outputs":{},"hostListeners":{},"hostProperties":{},"hostAttributes":{},"providers":[],"viewProviders":[],"queries":[],"guards":{},"viewQueries":[{"selectors":[{"value":"qrcElement"}],"first":true,"descendants":true,"propertyName":"qrcElement","read":null}],"entryComponents":[],"changeDetection":1,"template":{"ngContentSelectors":[],"encapsulation":2},"componentViewType":{"__symbol":4,"members":[]},"rendererType":{"__symbol":5,"members":[]},"componentFactory":{"__symbol":6,"members":[]}}}],"symbols":[{"__symbol":0,"name":"QrcodeComponent","filePath":"./qrcode"},{"__symbol":1,"name":"Input","filePath":"@angular/core/core"},{"__symbol":2,"name":"ViewChild","filePath":"@angular/core/core"},{"__symbol":3,"name":"Renderer2","filePath":"@angular/core/core"},{"__symbol":4,"name":"View_QrcodeComponent_0","filePath":"./qrcode.ngfactory"},{"__symbol":5,"name":"RenderType_QrcodeComponent","filePath":"./qrcode.ngfactory"},{"__symbol":6,"name":"QrcodeComponentNgFactory","filePath":"./qrcode.ngfactory"}]}