[{"__symbolic":"module","version":4,"metadata":{"IonWechatDirectivesModule":{"__symbolic":"class","decorators":[{"__symbolic":"call","expression":{"__symbolic":"reference","module":"@angular/core","name":"NgModule","line":3,"character":1},"arguments":[{"declarations":[{"__symbolic":"reference","module":"./sticky/sticky","name":"StickyDirective","line":4,"character":17}],"imports":[],"exports":[{"__symbolic":"reference","module":"./sticky/sticky","name":"StickyDirective","line":6,"character":12}]}]}]}}}]